MANIFEST.in
README.md
pyproject.toml
MindPype.egg-info/PKG-INFO
MindPype.egg-info/SOURCES.txt
MindPype.egg-info/dependency_links.txt
MindPype.egg-info/requires.txt
MindPype.egg-info/top_level.txt
doc/conf.py
mindpype/__init__.py
mindpype/classifier.py
mindpype/containers.py
mindpype/core.py
mindpype/filter.py
mindpype/graph.py
mindpype/kernel.py
mindpype/source.py
mindpype/kernels/__init__.py
mindpype/kernels/arithmetic.py
mindpype/kernels/baseline_correction.py
mindpype/kernels/classifier.py
mindpype/kernels/csp.py
mindpype/kernels/datamgmt.py
mindpype/kernels/feature_normalization.py
mindpype/kernels/filters.py
mindpype/kernels/kernel_utils.py
mindpype/kernels/logical.py
mindpype/kernels/pad.py
mindpype/kernels/reduced_sum.py
mindpype/kernels/resample.py
mindpype/kernels/riemann_distance.py
mindpype/kernels/riemann_mdm_classifier_kernel.py
mindpype/kernels/riemann_mean.py
mindpype/kernels/riemann_potato.py
mindpype/kernels/running_average.py
mindpype/kernels/statistics.py
mindpype/kernels/tangent_space.py
mindpype/kernels/threshold.py
mindpype/kernels/transpose.py
mindpype/kernels/xdawn_covariances.py